py_cli_interaction/__init__.py
py_cli_interaction/interaction.py
py_cli_interaction-0.3.dist-info/LICENSE
py_cli_interaction-0.3.dist-info/METADATA
py_cli_interaction-0.3.dist-info/WHEEL
py_cli_interaction-0.3.dist-info/top_level.txt
py_cli_interaction-0.3.dist-info/RECORD
