Metadata-Version: 2.1
Name: py-cli-interaction
Version: 0.3
Summary: A library for CLI interaction
Author: davidliyutong
Author-email: davidliyutong@sjtu.edu.cn
License: MIT Licence
Keywords: python,CLI,interaction
Requires-Python: >=3.7
License-File: LICENSE
Requires-Dist: rich (>=11.0.0)
